uw_restclients_sps_contacts-1.0.9.dist-info/licenses/LICENSE
uw_sps_contacts/VERSION
uw_sps_contacts/__init__.py
uw_sps_contacts/dao.py
uw_sps_contacts/models.py
uw_sps_contacts/test.py
uw_sps_contacts/utils.py
uw_sps_contacts/resources/sps_contacts/file/contacts/v1/emergencyContacts/12345
uw_sps_contacts/resources/sps_contacts/file/student/registration/v1/address/12345
uw_sps_contacts/resources/sps_contacts_auth/file/oauth2/token.POST
uw_sps_contacts/tests/__init__.py
uw_sps_contacts/tests/test_dao.py
uw_sps_contacts/tests/test_emergency_contacts.py
uw_sps_contacts/tests/test_family_contact.py
uw_restclients_sps_contacts-1.0.9.dist-info/METADATA
uw_restclients_sps_contacts-1.0.9.dist-info/WHEEL
uw_restclients_sps_contacts-1.0.9.dist-info/top_level.txt
uw_restclients_sps_contacts-1.0.9.dist-info/RECORD
