Metadata-Version: 2.4
Name: UW-RestClients-SPS-Contacts
Version: 1.0.9
Summary: A library for connecting to student contact services at the University of Washington
Home-page: https://github.com/uw-it-aca/uw-restclients-sps-contacts
Author: UW-IT Student & Educational Technology Services
Author-email: aca-it@uw.edu
License: Apache License, Version 2.0
Classifier: Intended Audience :: Developers
Classifier: License :: OSI Approved :: Apache Software License
Classifier: Operating System :: OS Independent
Classifier: Programming Language :: Python
License-File: LICENSE
Requires-Dist: UW-RestClients-Core
Dynamic: author
Dynamic: author-email
Dynamic: classifier
Dynamic: description
Dynamic: home-page
Dynamic: license
Dynamic: license-file
Dynamic: requires-dist
Dynamic: summary
